funnyreason/__init__.py
funnyreason/reasons.py
funnyreason-0.1.0.dist-info/licenses/LICENSE
funnyreason-0.1.0.dist-info/METADATA
funnyreason-0.1.0.dist-info/WHEEL
funnyreason-0.1.0.dist-info/top_level.txt
funnyreason-0.1.0.dist-info/RECORD
