Metadata-Version: 2.4
Name: funnyreason
Version: 0.1.0
Summary: A simple package that gives a random funny reason for anything.
Author-email: AJ <your_email@example.com>
License: MIT
Project-URL: Homepage, https://pypi.org/project/funnyreason/
Requires-Python: >=3.7
License-File: LICENSE
Dynamic: license-file
